{"GoodreadsResponse": {"Request": {"authentication": "true", "key": "UEjJ8JPVjwhYdPBBzZw", "method": "series_list"}, "series_works": {"series_work": [{"id": "483595", "user_position": null, "series": {"id": "99873", "title": "History's Kid Heroes", "description": null, "note": null, "series_works_count": "7", "primary_work_count": "7", "numbered": "false"}, "work": {"id": "13546899", "best_book": {"id": "8675029", "title": "The LifeSaving Adventure of Sam Deal, Shipwreck Rescuer", "author": {"id": "5353829", "name": "Candice Ransom"}, "image_url": "https://s.gr-assets.com/assets/nophoto/book/111x148-bcc042a9c91a29c1d680899eff700a03.png"}, "books_count": "4", "original_publication_day": null, "original_publication_month": "8", "original_publication_year": "2010", "original_title": null, "ratings_count": "6", "ratings_sum": "17", "reviews_count": "8", "text_reviews_count": "1", "average_rating": null}}, {"id": "409000", "user_position": null, "series": {"id": "85228", "title": "History Speaks: Picture Books Plus Reader's Theater", "description": "Bring to life important stories from U.S. history with the History Speaks: Picture Books Plus Reader\u2019s Theater. These books bring together illustrated picture books with readers's theater scripts for students to practice fluency", "note": null, "series_works_count": "12", "primary_work_count": "12", "numbered": "false"}, "work": {"id": "15351960", "best_book": {"id": "10447215", "title": "Alice Ray and the Salem Witch Trials", "author": {"id": "80648", "name": "Shannon Knudsen"}, "image_url": "https://s.gr-assets.com/assets/nophoto/book/111x148-bcc042a9c91a29c1d680899eff700a03.png"}, "books_count": "4", "original_publication_day": "1", "original_publication_month": "8", "original_publication_year": "2010", "original_title": null, "ratings_count": "1", "ratings_sum": "3", "reviews_count": "12", "text_reviews_count": "4", "average_rating": null}}, {"id": "494998", "user_position": "1", "series": {"id": "102322", "title": "The Decades of Twentieth-Century America", "description": null, "note": null, "series_works_count": "10", "primary_work_count": "10", "numbered": "true"}, "work": {"id": "9429138", "best_book": {"id": "7435679", "title": "America In The 1900s (The Decades Of Twentieth Century America)", "author": {"id": "1490", "name": "Marlene Targ Brill"}, "image_url": "https://s.gr-assets.com/assets/nophoto/book/111x148-bcc042a9c91a29c1d680899eff700a03.png"}, "books_count": "1", "original_publication_day": "1", "original_publication_month": "9", "original_publication_year": "2009", "original_title": null, "ratings_count": "7", "ratings_sum": "23", "reviews_count": "14", "text_reviews_count": "1", "average_rating": null}}, {"id": "483596", "user_position": null, "series": {"id": "99873", "title": "History's Kid Heroes", "description": null, "note": null, "series_works_count": "7", "primary_work_count": "7", "numbered": "false"}, "work": {"id": "17460732", "best_book": {"id": "12476390", "title": "The Prairie Adventure of Sarah and Annie, Blizzard Survivors", "author": {"id": "285029", "name": "Marty Rhodes Figley"}, "image_url": "https://s.gr-assets.com/assets/nophoto/book/111x148-bcc042a9c91a29c1d680899eff700a03.png"}, "books_count": "7", "original_publication_day": "1", "original_publication_month": "8", "original_publication_year": "2011", "original_title": null, "ratings_count": "6", "ratings_sum": "24", "reviews_count": "8", "text_reviews_count": "1", "average_rating": null}}, {"id": "409001", "user_position": null, "series": {"id": "85228", "title": "History Speaks: Picture Books Plus Reader's Theater", "description": "Bring to life important stories from U.S. history with the History Speaks: Picture Books Plus Reader\u2019s Theater. These books bring together illustrated picture books with readers's theater scripts for students to practice fluency", "note": null, "series_works_count": "12", "primary_work_count": "12", "numbered": "false"}, "work": {"id": "12787941", "best_book": {"id": "8075069", "title": "Annie Shapiro and the Clothing Workers' Strike", "author": {"id": "1490", "name": "Marlene Targ Brill"}, "image_url": "https://s.gr-assets.com/assets/nophoto/book/111x148-bcc042a9c91a29c1d680899eff700a03.png"}, "books_count": "3", "original_publication_day": "1", "original_publication_month": "8", "original_publication_year": "2010", "original_title": null, "ratings_count": "5", "ratings_sum": "20", "reviews_count": "17", "text_reviews_count": "2", "average_rating": null}}, {"id": "343489", "user_position": null, "series": {"id": "74376", "title": "Gateway Biography", "description": null, "note": null, "series_works_count": "18", "primary_work_count": "18", "numbered": "false"}, "work": {"id": "5446781", "best_book": {"id": "5379266", "title": "Al Gore: Fighting for a Greener Planet", "author": {"id": "15229", "name": "Rebecca Stefoff"}, "image_url": "https://s.gr-assets.com/assets/nophoto/book/111x148-bcc042a9c91a29c1d680899eff700a03.png"}, "books_count": "2", "original_publication_day": "1", "original_publication_month": "9", "original_publication_year": "2008", "original_title": "Al Gore: Fighting for a Greener Planet (Gateway Biographies)", "ratings_count": "16", "ratings_sum": "32", "reviews_count": "29", "text_reviews_count": "1", "average_rating": null}}, {"id": "256947", "user_position": null, "series": {"id": "60275", "title": "On My Own History", "description": null, "note": null, "series_works_count": "30", "primary_work_count": "30", "numbered": "false"}, "work": {"id": "1108376", "best_book": {"id": "1121294", "title": "Allen Jay and the Underground Railroad (On My Own History)", "author": {"id": "1490", "name": "Marlene Targ Brill"}, "image_url": "https://s.gr-assets.com/assets/nophoto/book/111x148-bcc042a9c91a29c1d680899eff700a03.png"}, "books_count": "17", "original_publication_day": "1", "original_publication_month": "1", "original_publication_year": "1993", "original_title": "Allen Jay and the Underground Railroad (On My Own History)", "ratings_count": "55", "ratings_sum": "215", "reviews_count": "136", "text_reviews_count": "3", "average_rating": null}}, {"id": "494999", "user_position": "2", "series": {"id": "102322", "title": "The Decades of Twentieth-Century America", "description": null, "note": null, "series_works_count": "10", "primary_work_count": "10", "numbered": "true"}, "work": {"id": "7005494", "best_book": {"id": "6799526", "title": "America In The 1910s", "author": {"id": "2283788", "name": "Marlee Richards"}, "image_url": "https://s.gr-assets.com/assets/nophoto/book/111x148-bcc042a9c91a29c1d680899eff700a03.png"}, "books_count": "1", "original_publication_day": "1", "original_publication_month": "9", "original_publication_year": "2009", "original_title": null, "ratings_count": "1", "ratings_sum": "3", "reviews_count": "10", "text_reviews_count": "0", "average_rating": null}}, {"id": "483597", "user_position": null, "series": {"id": "99873", "title": "History's Kid Heroes", "description": null, "note": null, "series_works_count": "7", "primary_work_count": "7", "numbered": "false"}, "work": {"id": "13739587", "best_book": {"id": "8864237", "title": "The Stormy Adventure of Abbie Burgess, Lighthouse Keeper", "author": {"id": "2692", "name": "Peter Roop"}, "image_url": "https://s.gr-assets.com/assets/nophoto/book/111x148-bcc042a9c91a29c1d680899eff700a03.png"}, "books_count": "4", "original_publication_day": "1", "original_publication_month": "8", "original_publication_year": "2010", "original_title": null, "ratings_count": "10", "ratings_sum": "31", "reviews_count": "13", "text_reviews_count": "3", "average_rating": null}}, {"id": "409002", "user_position": null, "series": {"id": "85228", "title": "History Speaks: Picture Books Plus Reader's Theater", "description": "Bring to life important stories from U.S. history with the History Speaks: Picture Books Plus Reader\u2019s Theater. These books bring together illustrated picture books with readers's theater scripts for students to practice fluency", "note": null, "series_works_count": "12", "primary_work_count": "12", "numbered": "false"}, "work": {"id": "14978556", "best_book": {"id": "11945593", "title": "Benjamin Brown and the Great Steamboat Race", "author": {"id": "333960", "name": "Shirley Jordan"}, "image_url": "https://s.gr-assets.com/assets/nophoto/book/111x148-bcc042a9c91a29c1d680899eff700a03.png"}, "books_count": "4", "original_publication_day": "1", "original_publication_month": "8", "original_publication_year": "2010", "original_title": null, "ratings_count": "1", "ratings_sum": "3", "reviews_count": "2", "text_reviews_count": "1", "average_rating": null}}, {"id": "343480", "user_position": null, "series": {"id": "74376", "title": "Gateway Biography", "description": null, "note": null, "series_works_count": "18", "primary_work_count": "18", "numbered": "false"}, "work": {"id": "5275793", "best_book": {"id": "5208615", "title": "Alberto Gonzales: Attorney General", "author": {"id": "60084", "name": "Lisa Tucker McElroy"}, "image_url": "https://s.gr-assets.com/assets/nophoto/book/111x148-bcc042a9c91a29c1d680899eff700a03.png"}, "books_count": "2", "original_publication_day": null, "original_publication_month": null, "original_publication_year": "2006", "original_title": "Alberto Gonzales: Attorney General (Gateway Biographies)", "ratings_count": "0", "ratings_sum": "0", "reviews_count": "4", "text_reviews_count": "0", "average_rating": null}}, {"id": "256948", "user_position": null, "series": {"id": "60275", "title": "On My Own History", "description": null, "note": null, "series_works_count": "30", "primary_work_count": "30", "numbered": "false"}, "work": {"id": "1014239", "best_book": {"id": "1027986", "title": "An American Army of Two (On My Own History)", "author": {"id": "301074", "name": "Janet Greeson"}, "image_url": "https://s.gr-assets.com/assets/nophoto/book/111x148-bcc042a9c91a29c1d680899eff700a03.png"}, "books_count": "7", "original_publication_day": null, "original_publication_month": "11", "original_publication_year": "1991", "original_title": "An American Army of Two (On My Own Books)", "ratings_count": "17", "ratings_sum": "64", "reviews_count": "34", "text_reviews_count": "3", "average_rating": null}}, {"id": "495000", "user_position": "3", "series": {"id": "102322", "title": "The Decades of Twentieth-Century America", "description": null, "note": null, "series_works_count": "10", "primary_work_count": "10", "numbered": "true"}, "work": {"id": "4343355", "best_book": {"id": "4295769", "title": "America in the 1920s", "author": {"id": "262599", "name": "Edmund Lindop"}, "image_url": "https://s.gr-assets.com/assets/nophoto/book/111x148-bcc042a9c91a29c1d680899eff700a03.png"}, "books_count": "1", "original_publication_day": "13", "original_publication_month": "8", "original_publication_year": "2004", "original_title": "America In The 1920s (20th-Century America)", "ratings_count": "4", "ratings_sum": "15", "reviews_count": "14", "text_reviews_count": "0", "average_rating": null}}, {"id": "483598", "user_position": null, "series": {"id": "99873", "title": "History's Kid Heroes", "description": null, "note": null, "series_works_count": "7", "primary_work_count": "7", "numbered": "false"}, "work": {"id": "14323802", "best_book": {"id": "9439198", "title": "The Top-Secret Adventure of John Darragh, Revolutionary War Spy (History's Kid Heroes)", "author": {"id": "2692", "name": "Peter Roop"}, "image_url": "https://s.gr-assets.com/assets/nophoto/book/111x148-bcc042a9c91a29c1d680899eff700a03.png"}, "books_count": "4", "original_publication_day": null, "original_publication_month": "8", "original_publication_year": "2010", "original_title": null, "ratings_count": "8", "ratings_sum": "25", "reviews_count": "22", "text_reviews_count": "2", "average_rating": null}}, {"id": "409003", "user_position": null, "series": {"id": "85228", "title": "History Speaks: Picture Books Plus Reader's Theater", "description": "Bring to life important stories from U.S. history with the History Speaks: Picture Books Plus Reader\u2019s Theater. These books bring together illustrated picture books with readers's theater scripts for students to practice fluency", "note": null, "series_works_count": "12", "primary_work_count": "12", "numbered": "false"}, "work": {"id": "14514651", "best_book": {"id": "9627374", "title": "Clara Morgan and the Oregon Trail Journey", "author": {"id": "285029", "name": "Marty Rhodes Figley"}, "image_url": "https://d.gr-assets.com/books/1295641178m/9627374.jpg"}, "books_count": "4", "original_publication_day": "1", "original_publication_month": "8", "original_publication_year": "2010", "original_title": null, "ratings_count": "9", "ratings_sum": "41", "reviews_count": "12", "text_reviews_count": "0", "average_rating": null}}, {"id": "343490", "user_position": null, "series": {"id": "74376", "title": "Gateway Biography", "description": null, "note": null, "series_works_count": "18", "primary_work_count": "18", "numbered": "false"}, "work": {"id": "6478759", "best_book": {"id": "6294379", "title": "Barack Obama: President for a New Era", "author": {"id": "1490", "name": "Marlene Targ Brill"}, "image_url": "https://s.gr-assets.com/assets/nophoto/book/111x148-bcc042a9c91a29c1d680899eff700a03.png"}, "books_count": "1", "original_publication_day": "1", "original_publication_month": "5", "original_publication_year": "2009", "original_title": "Barack Obama: President for a New Era (Gateway Biographies)", "ratings_count": "6", "ratings_sum": "24", "reviews_count": "7", "text_reviews_count": "1", "average_rating": null}}, {"id": "256949", "user_position": null, "series": {"id": "60275", "title": "On My Own History", "description": null, "note": null, "series_works_count": "30", "primary_work_count": "30", "numbered": "false"}, "work": {"id": "456380", "best_book": {"id": "468036", "title": "Bronco Charlie and the Pony Express", "author": {"id": "1490", "name": "Marlene Targ Brill"}, "image_url": "https://s.gr-assets.com/assets/nophoto/book/111x148-bcc042a9c91a29c1d680899eff700a03.png"}, "books_count": "8", "original_publication_day": null, "original_publication_month": null, "original_publication_year": "2004", "original_title": "Bronco Charlie and the Pony Express (On My Own History)", "ratings_count": "12", "ratings_sum": "43", "reviews_count": "31", "text_reviews_count": "1", "average_rating": null}}, {"id": "495001", "user_position": "4", "series": {"id": "102322", "title": "The Decades of Twentieth-Century America", "description": null, "note": null, "series_works_count": "10", "primary_work_count": "10", "numbered": "true"}, "work": {"id": "3725082", "best_book": {"id": "3681700", "title": "America in the 1930s", "author": {"id": "262599", "name": "Edmund Lindop"}, "image_url": "https://s.gr-assets.com/assets/nophoto/book/111x148-bcc042a9c91a29c1d680899eff700a03.png"}, "books_count": "1", "original_publication_day": "30", "original_publication_month": "9", "original_publication_year": "2008", "original_title": "America in the 1930s", "ratings_count": "5", "ratings_sum": "20", "reviews_count": "11", "text_reviews_count": "1", "average_rating": null}}, {"id": "483599", "user_position": null, "series": {"id": "99873", "title": "History's Kid Heroes", "description": null, "note": null, "series_works_count": "7", "primary_work_count": "7", "numbered": "false"}, "work": {"id": "13197993", "best_book": {"id": "8346509", "title": "The Snowshoeing Adventure of Milton Daub, Blizzard Trekker", "author": {"id": "124782", "name": "Margaret K. Wetterer"}, "image_url": "https://s.gr-assets.com/assets/nophoto/book/111x148-bcc042a9c91a29c1d680899eff700a03.png"}, "books_count": "5", "original_publication_day": null, "original_publication_month": "8", "original_publication_year": "2010", "original_title": null, "ratings_count": "5", "ratings_sum": "15", "reviews_count": "7", "text_reviews_count": "2", "average_rating": null}}, {"id": "343481", "user_position": null, "series": {"id": "74376", "title": "Gateway Biography", "description": null, "note": null, "series_works_count": "18", "primary_work_count": "18", "numbered": "false"}, "work": {"id": "1782793", "best_book": {"id": "1783925", "title": "Condoleezza Rice", "author": {"id": "203230", "name": "Mary Dodson Wade"}, "image_url": "https://s.gr-assets.com/assets/nophoto/book/111x148-bcc042a9c91a29c1d680899eff700a03.png"}, "books_count": "5", "original_publication_day": "16", "original_publication_month": "1", "original_publication_year": "2003", "original_title": "Condoleezza Rice : Being the Best", "ratings_count": "3", "ratings_sum": "11", "reviews_count": "12", "text_reviews_count": "0", "average_rating": null}}, {"id": "256951", "user_position": null, "series": {"id": "60275", "title": "On My Own History", "description": null, "note": null, "series_works_count": "30", "primary_work_count": "30", "numbered": "false"}, "work": {"id": "2929545", "best_book": {"id": "705819", "title": "Buttons for General Washington (On My Own History)", "author": {"id": "2692", "name": "Peter Roop"}, "image_url": "https://s.gr-assets.com/assets/nophoto/book/111x148-bcc042a9c91a29c1d680899eff700a03.png"}, "books_count": "17", "original_publication_day": "1", "original_publication_month": "1", "original_publication_year": "1986", "original_title": "Buttons for General Washington (On My Own History)", "ratings_count": "52", "ratings_sum": "197", "reviews_count": "109", "text_reviews_count": "15", "average_rating": null}}, {"id": "495002", "user_position": "5", "series": {"id": "102322", "title": "The Decades of Twentieth-Century America", "description": null, "note": null, "series_works_count": "10", "primary_work_count": "10", "numbered": "true"}, "work": {"id": "3767219", "best_book": {"id": "3723477", "title": "America in the 1940s", "author": {"id": "262599", "name": "Edmund Lindop"}, "image_url": "https://s.gr-assets.com/assets/nophoto/book/111x148-bcc042a9c91a29c1d680899eff700a03.png"}, "books_count": "1", "original_publication_day": "1", "original_publication_month": "9", "original_publication_year": "2009", "original_title": "America in the 1940s (20th-Century America)", "ratings_count": "5", "ratings_sum": "21", "reviews_count": "13", "text_reviews_count": "1", "average_rating": null}}, {"id": "483600", "user_position": null, "series": {"id": "99873", "title": "History's Kid Heroes", "description": null, "note": null, "series_works_count": "7", "primary_work_count": "7", "numbered": "false"}, "work": {"id": "12273556", "best_book": {"id": "7976015", "title": "The Rough-Riding Adventure of Bronco Charlie, Pony Express Rider", "author": {"id": "1490", "name": "Marlene Targ Brill"}, "image_url": "https://s.gr-assets.com/assets/nophoto/book/111x148-bcc042a9c91a29c1d680899eff700a03.png"}, "books_count": "4", "original_publication_day": "1", "original_publication_month": "7", "original_publication_year": "2010", "original_title": null, "ratings_count": "2", "ratings_sum": "6", "reviews_count": "5", "text_reviews_count": "1", "average_rating": null}}, {"id": "409005", "user_position": null, "series": {"id": "85228", "title": "History Speaks: Picture Books Plus Reader's Theater", "description": "Bring to life important stories from U.S. history with the History Speaks: Picture Books Plus Reader\u2019s Theater. These books bring together illustrated picture books with readers's theater scripts for students to practice fluency", "note": null, "series_works_count": "12", "primary_work_count": "12", "numbered": "false"}, "work": {"id": "15387106", "best_book": {"id": "10481644", "title": "Ellen Craft's Escape from Slavery", "author": {"id": "358253", "name": "Cathy Moore"}, "image_url": "https://s.gr-assets.com/assets/nophoto/book/111x148-bcc042a9c91a29c1d680899eff700a03.png"}, "books_count": "3", "original_publication_day": "1", "original_publication_month": "7", "original_publication_year": "2010", "original_title": null, "ratings_count": "4", "ratings_sum": "16", "reviews_count": "7", "text_reviews_count": "3", "average_rating": null}}, {"id": "256953", "user_position": null, "series": {"id": "60275", "title": "On My Own History", "description": null, "note": null, "series_works_count": "30", "primary_work_count": "30", "numbered": "false"}, "work": {"id": "3486429", "best_book": {"id": "3445326", "title": "Clouds of Terror (On My Own History)", "author": {"id": "119012", "name": "Catherine A. Welch"}, "image_url": "https://s.gr-assets.com/assets/nophoto/book/111x148-bcc042a9c91a29c1d680899eff700a03.png"}, "books_count": "6", "original_publication_day": null, "original_publication_month": "4", "original_publication_year": "1994", "original_title": "Clouds of Terror (On My Own History)", "ratings_count": "15", "ratings_sum": "60", "reviews_count": "43", "text_reviews_count": "0", "average_rating": null}}, {"id": "495003", "user_position": "6", "series": {"id": "102322", "title": "The Decades of Twentieth-Century America", "description": null, "note": null, "series_works_count": "10", "primary_work_count": "10", "numbered": "true"}, "work": {"id": "8141560", "best_book": {"id": "7236188", "title": "America in the 1950s", "author": {"id": "262599", "name": "Edmund Lindop"}, "image_url": "https://s.gr-assets.com/assets/nophoto/book/111x148-bcc042a9c91a29c1d680899eff700a03.png"}, "books_count": "2", "original_publication_day": "1", "original_publication_month": "9", "original_publication_year": "2002", "original_title": null, "ratings_count": "4", "ratings_sum": "15", "reviews_count": "19", "text_reviews_count": "1", "average_rating": null}}, {"id": "483601", "user_position": null, "series": {"id": "99873", "title": "History's Kid Heroes", "description": null, "note": null, "series_works_count": "7", "primary_work_count": "7", "numbered": "false"}, "work": {"id": "13197995", "best_book": {"id": "8346511", "title": "The Midnight Adventure of Kate Shelley, Train Rescuer", "author": {"id": "124782", "name": "Margaret K. Wetterer"}, "image_url": "https://s.gr-assets.com/assets/nophoto/book/111x148-bcc042a9c91a29c1d680899eff700a03.png"}, "books_count": "4", "original_publication_day": "1", "original_publication_month": "7", "original_publication_year": "2010", "original_title": null, "ratings_count": "0", "ratings_sum": "0", "reviews_count": "2", "text_reviews_count": "0", "average_rating": null}}, {"id": "409006", "user_position": null, "series": {"id": "85228", "title": "History Speaks: Picture Books Plus Reader's Theater", "description": "Bring to life important stories from U.S. history with the History Speaks: Picture Books Plus Reader\u2019s Theater. These books bring together illustrated picture books with readers's theater scripts for students to practice fluency", "note": null, "series_works_count": "12", "primary_work_count": "12", "numbered": "false"}, "work": {"id": "13055378", "best_book": {"id": "8208276", "title": "Enrique Esparza and the Battle of the Alamo", "author": {"id": "137836", "name": "Susan Taylor Brown"}, "image_url": "https://s.gr-assets.com/assets/nophoto/book/111x148-bcc042a9c91a29c1d680899eff700a03.png"}, "books_count": "3", "original_publication_day": null, "original_publication_month": "8", "original_publication_year": "2010", "original_title": null, "ratings_count": "3", "ratings_sum": "15", "reviews_count": "5", "text_reviews_count": "1", "average_rating": null}}, {"id": "343479", "user_position": null, "series": {"id": "74376", "title": "Gateway Biography", "description": null, "note": null, "series_works_count": "18", "primary_work_count": "18", "numbered": "false"}, "work": {"id": "1816041", "best_book": {"id": "1816531", "title": "Elie Wiesel: Bearing Witness (Gateway Biography)", "author": {"id": "4193473", "name": "Michael Pariser"}, "image_url": "https://s.gr-assets.com/assets/nophoto/book/111x148-bcc042a9c91a29c1d680899eff700a03.png"}, "books_count": "2", "original_publication_day": null, "original_publication_month": null, "original_publication_year": "1994", "original_title": "Elie Wiesel (Gateway Biography)", "ratings_count": "9", "ratings_sum": "41", "reviews_count": "34", "text_reviews_count": "1", "average_rating": null}}, {"id": "256954", "user_position": null, "series": {"id": "60275", "title": "On My Own History", "description": null, "note": null, "series_works_count": "30", "primary_work_count": "30", "numbered": "false"}, "work": {"id": "1460014", "best_book": {"id": "1469078", "title": "The Copper Lady (On My Own History)", "author": {"id": "688524", "name": "Alice Ross"}, "image_url": "https://s.gr-assets.com/assets/nophoto/book/111x148-bcc042a9c91a29c1d680899eff700a03.png"}, "books_count": "6", "original_publication_day": "1", "original_publication_month": "10", "original_publication_year": "1996", "original_title": "The Copper Lady", "ratings_count": "20", "ratings_sum": "77", "reviews_count": "50", "text_reviews_count": "4", "average_rating": null}}, {"id": "495004", "user_position": "7", "series": {"id": "102322", "title": "The Decades of Twentieth-Century America", "description": null, "note": null, "series_works_count": "10", "primary_work_count": "10", "numbered": "true"}, "work": {"id": "9367521", "best_book": {"id": "7419284", "title": "America in the 1960s", "author": {"id": "262599", "name": "Edmund Lindop"}, "image_url": "https://s.gr-assets.com/assets/nophoto/book/111x148-bcc042a9c91a29c1d680899eff700a03.png"}, "books_count": "1", "original_publication_day": "1", "original_publication_month": "9", "original_publication_year": "2009", "original_title": null, "ratings_count": "3", "ratings_sum": "11", "reviews_count": "10", "text_reviews_count": "0", "average_rating": null}}, {"id": "409007", "user_position": null, "series": {"id": "85228", "title": "History Speaks: Picture Books Plus Reader's Theater", "description": "Bring to life important stories from U.S. history with the History Speaks: Picture Books Plus Reader\u2019s Theater. These books bring together illustrated picture books with readers's theater scripts for students to practice fluency", "note": null, "series_works_count": "12", "primary_work_count": "12", "numbered": "false"}, "work": {"id": "15746205", "best_book": {"id": "10832175", "title": "George Washington and the Story of the U.S. Constitution", "author": {"id": "5353829", "name": "Candice Ransom"}, "image_url": "https://s.gr-assets.com/assets/nophoto/book/111x148-bcc042a9c91a29c1d680899eff700a03.png"}, "books_count": "6", "original_publication_day": "1", "original_publication_month": "8", "original_publication_year": "2010", "original_title": null, "ratings_count": "0", "ratings_sum": "0", "reviews_count": "1", "text_reviews_count": "0", "average_rating": null}}, {"id": "343483", "user_position": null, "series": {"id": "74376", "title": "Gateway Biography", "description": null, "note": null, "series_works_count": "18", "primary_work_count": "18", "numbered": "false"}, "work": {"id": "1566818", "best_book": {"id": "1574099", "title": "George W. Bush: Family Business (Gateway Biographies)", "author": {"id": "40652", "name": "Daniel   Cohen"}, "image_url": "https://s.gr-assets.com/assets/nophoto/book/111x148-bcc042a9c91a29c1d680899eff700a03.png"}, "books_count": "3", "original_publication_day": "1", "original_publication_month": "1", "original_publication_year": "2000", "original_title": "George W. Bush: Family Business", "ratings_count": "0", "ratings_sum": "0", "reviews_count": "3", "text_reviews_count": "0", "average_rating": null}}, {"id": "256956", "user_position": null, "series": {"id": "60275", "title": "On My Own History", "description": null, "note": null, "series_works_count": "30", "primary_work_count": "30", "numbered": "false"}, "work": {"id": "366781", "best_book": {"id": "376937", "title": "Cracking the Wall: The Struggles of the Little Rock Nine", "author": {"id": "118945", "name": "Eileen Lucas"}, "image_url": "https://s.gr-assets.com/assets/nophoto/book/111x148-bcc042a9c91a29c1d680899eff700a03.png"}, "books_count": "15", "original_publication_day": "1", "original_publication_month": "10", "original_publication_year": "1997", "original_title": "Cracking the Wall: The Struggles of the Little Rock Nine", "ratings_count": "15", "ratings_sum": "56", "reviews_count": "38", "text_reviews_count": "4", "average_rating": null}}, {"id": "495005", "user_position": "8", "series": {"id": "102322", "title": "The Decades of Twentieth-Century America", "description": null, "note": null, "series_works_count": "10", "primary_work_count": "10", "numbered": "true"}, "work": {"id": "5382523", "best_book": {"id": "5315054", "title": "America in the 1970s", "author": {"id": "2283788", "name": "Marlee Richards"}, "image_url": "https://s.gr-assets.com/assets/nophoto/book/111x148-bcc042a9c91a29c1d680899eff700a03.png"}, "books_count": "1", "original_publication_day": null, "original_publication_month": "9", "original_publication_year": "2008", "original_title": "America in the 1970s", "ratings_count": "3", "ratings_sum": "12", "reviews_count": "10", "text_reviews_count": "1", "average_rating": null}}, {"id": "409008", "user_position": null, "series": {"id": "85228", "title": "History Speaks: Picture Books Plus Reader's Theater", "description": "Bring to life important stories from U.S. history with the History Speaks: Picture Books Plus Reader\u2019s Theater. These books bring together illustrated picture books with readers's theater scripts for students to practice fluency", "note": null, "series_works_count": "12", "primary_work_count": "12", "numbered": "false"}, "work": {"id": "14405772", "best_book": {"id": "9519833", "title": "John Greenwood's Journey to Bunker Hill", "author": {"id": "285029", "name": "Marty Rhodes Figley"}, "image_url": "https://s.gr-assets.com/assets/nophoto/book/111x148-bcc042a9c91a29c1d680899eff700a03.png"}, "books_count": "3", "original_publication_day": null, "original_publication_month": "8", "original_publication_year": "2010", "original_title": null, "ratings_count": "2", "ratings_sum": "9", "reviews_count": "3", "text_reviews_count": "0", "average_rating": null}}, {"id": "343484", "user_position": null, "series": {"id": "74376", "title": "Gateway Biography", "description": null, "note": null, "series_works_count": "18", "primary_work_count": "18", "numbered": "false"}, "work": {"id": "85531", "best_book": {"id": "88629", "title": "Hillary Rodham Clinton (Gateway Biography)", "author": {"id": "22787", "name": "Suzanne LeVert"}, "image_url": "https://s.gr-assets.com/assets/nophoto/book/111x148-bcc042a9c91a29c1d680899eff700a03.png"}, "books_count": "3", "original_publication_day": "1", "original_publication_month": "1", "original_publication_year": "1998", "original_title": "Hillary Rodham Clinton Revd Ed (Gateway Biographies)", "ratings_count": "1", "ratings_sum": "4", "reviews_count": "3", "text_reviews_count": "1", "average_rating": null}}, {"id": "256957", "user_position": null, "series": {"id": "60275", "title": "On My Own History", "description": null, "note": null, "series_works_count": "30", "primary_work_count": "30", "numbered": "false"}, "work": {"id": "1010382", "best_book": {"id": "1023763", "title": "Danger at Sand Cave (On My Own History)", "author": {"id": "5353829", "name": "Candice Ransom"}, "image_url": "https://s.gr-assets.com/assets/nophoto/book/111x148-bcc042a9c91a29c1d680899eff700a03.png"}, "books_count": "5", "original_publication_day": null, "original_publication_month": null, "original_publication_year": "2000", "original_title": "Danger at Sand Cave (On My Own History)", "ratings_count": "3", "ratings_sum": "12", "reviews_count": "10", "text_reviews_count": "0", "average_rating": null}}, {"id": "495006", "user_position": "9", "series": {"id": "102322", "title": "The Decades of Twentieth-Century America", "description": null, "note": null, "series_works_count": "10", "primary_work_count": "10", "numbered": "true"}, "work": {"id": "9429137", "best_book": {"id": "7435678", "title": "America in the 1980s", "author": {"id": "1490", "name": "Marlene Targ Brill"}, "image_url": "https://s.gr-assets.com/assets/nophoto/book/111x148-bcc042a9c91a29c1d680899eff700a03.png"}, "books_count": "1", "original_publication_day": null, "original_publication_month": null, "original_publication_year": "2009", "original_title": null, "ratings_count": "3", "ratings_sum": "9", "reviews_count": "11", "text_reviews_count": "2", "average_rating": null}}, {"id": "409009", "user_position": null, "series": {"id": "85228", "title": "History Speaks: Picture Books Plus Reader's Theater", "description": "Bring to life important stories from U.S. history with the History Speaks: Picture Books Plus Reader\u2019s Theater. These books bring together illustrated picture books with readers's theater scripts for students to practice fluency", "note": null, "series_works_count": "12", "primary_work_count": "12", "numbered": "false"}, "work": {"id": "15788056", "best_book": {"id": "10872753", "title": "Johnny Moore and the Wright Brothers' Flying Machine", "author": {"id": "1130197", "name": "Walter A. Schulz"}, "image_url": "https://s.gr-assets.com/assets/nophoto/book/111x148-bcc042a9c91a29c1d680899eff700a03.png"}, "books_count": "5", "original_publication_day": "1", "original_publication_month": "8", "original_publication_year": "2010", "original_title": null, "ratings_count": "0", "ratings_sum": "0", "reviews_count": "1", "text_reviews_count": "0", "average_rating": null}}, {"id": "343491", "user_position": null, "series": {"id": "74376", "title": "Gateway Biography", "description": null, "note": null, "series_works_count": "18", "primary_work_count": "18", "numbered": "false"}, "work": {"id": "17243129", "best_book": {"id": "12267970", "title": "Jennifer Lawrence: Star of the Hunger Games", "author": {"id": "3511", "name": "Katherine E. Krohn"}, "image_url": "https://d.gr-assets.com/books/1324434698m/12267970.jpg"}, "books_count": "4", "original_publication_day": "1", "original_publication_month": "1", "original_publication_year": "2012", "original_title": null, "ratings_count": "260", "ratings_sum": "1109", "reviews_count": "584", "text_reviews_count": "10", "average_rating": null}}, {"id": "256958", "user_position": null, "series": {"id": "60275", "title": "On My Own History", "description": null, "note": null, "series_works_count": "30", "primary_work_count": "30", "numbered": "false"}, "work": {"id": "653705", "best_book": {"id": "667657", "title": "The Daring Escape of Ellen Craft", "author": {"id": "358253", "name": "Cathy Moore"}, "image_url": "https://s.gr-assets.com/assets/nophoto/book/111x148-bcc042a9c91a29c1d680899eff700a03.png"}, "books_count": "7", "original_publication_day": "1", "original_publication_month": "1", "original_publication_year": "2002", "original_title": "The Daring Escape of Ellen Craft", "ratings_count": "17", "ratings_sum": "67", "reviews_count": "43", "text_reviews_count": "5", "average_rating": null}}, {"id": "495007", "user_position": "10", "series": {"id": "102322", "title": "The Decades of Twentieth-Century America", "description": null, "note": null, "series_works_count": "10", "primary_work_count": "10", "numbered": "true"}, "work": {"id": "13161336", "best_book": {"id": "8312184", "title": "America in the 1990s", "author": {"id": "1490", "name": "Marlene Targ Brill"}, "image_url": "https://s.gr-assets.com/assets/nophoto/book/111x148-bcc042a9c91a29c1d680899eff700a03.png"}, "books_count": "1", "original_publication_day": null, "original_publication_month": "9", "original_publication_year": "2009", "original_title": null, "ratings_count": "2", "ratings_sum": "5", "reviews_count": "7", "text_reviews_count": "1", "average_rating": null}}, {"id": "409010", "user_position": null, "series": {"id": "85228", "title": "History Speaks: Picture Books Plus Reader's Theater", "description": "Bring to life important stories from U.S. history with the History Speaks: Picture Books Plus Reader\u2019s Theater. These books bring together illustrated picture books with readers's theater scripts for students to practice fluency", "note": null, "series_works_count": "12", "primary_work_count": "12", "numbered": "false"}, "work": {"id": "15414002", "best_book": {"id": "10508102", "title": "The Little Rock Nine Stand Up for Their Rights", "author": {"id": "118945", "name": "Eileen Lucas"}, "image_url": "https://s.gr-assets.com/assets/nophoto/book/111x148-bcc042a9c91a29c1d680899eff700a03.png"}, "books_count": "4", "original_publication_day": "1", "original_publication_month": "8", "original_publication_year": "2010", "original_title": null, "ratings_count": "4", "ratings_sum": "15", "reviews_count": "11", "text_reviews_count": "2", "average_rating": null}}, {"id": "343485", "user_position": null, "series": {"id": "74376", "title": "Gateway Biography", "description": null, "note": null, "series_works_count": "18", "primary_work_count": "18", "numbered": "false"}, "work": {"id": "939590", "best_book": {"id": "954680", "title": "John G. Roberts, Jr.: Chief Justice", "author": {"id": "60084", "name": "Lisa Tucker McElroy"}, "image_url": "https://s.gr-assets.com/assets/nophoto/book/111x148-bcc042a9c91a29c1d680899eff700a03.png"}, "books_count": "2", "original_publication_day": "6", "original_publication_month": "10", "original_publication_year": "2006", "original_title": "John G. Roberts, Jr.: Chief Justice (Gateway Biographies)", "ratings_count": "1", "ratings_sum": "4", "reviews_count": "5", "text_reviews_count": "0", "average_rating": null}}, {"id": "354795", "user_position": null, "series": {"id": "60275", "title": "On My Own History", "description": null, "note": null, "series_works_count": "30", "primary_work_count": "30", "numbered": "false"}, "work": {"id": "4248668", "best_book": {"id": "6558565", "title": "The Day of the Black Blizzard (On My Own History)", "author": {"id": "5353829", "name": "Candice Ransom"}, "image_url": "https://s.gr-assets.com/assets/nophoto/book/111x148-bcc042a9c91a29c1d680899eff700a03.png"}, "books_count": "6", "original_publication_day": "1", "original_publication_month": "1", "original_publication_year": "2009", "original_title": "The Day of the Black Blizzard (On My Own History)", "ratings_count": "3", "ratings_sum": "10", "reviews_count": "8", "text_reviews_count": "0", "average_rating": null}}, {"id": "409011", "user_position": null, "series": {"id": "85228", "title": "History Speaks: Picture Books Plus Reader's Theater", "description": "Bring to life important stories from U.S. history with the History Speaks: Picture Books Plus Reader\u2019s Theater. These books bring together illustrated picture books with readers's theater scripts for students to practice fluency", "note": null, "series_works_count": "12", "primary_work_count": "12", "numbered": "false"}, "work": {"id": "12945293", "best_book": {"id": "8146520", "title": "Lizzie Newton and the San Francisco Earthquake", "author": {"id": "24657", "name": "Stephen Krensky"}, "image_url": "https://s.gr-assets.com/assets/nophoto/book/111x148-bcc042a9c91a29c1d680899eff700a03.png"}, "books_count": "4", "original_publication_day": "1", "original_publication_month": "8", "original_publication_year": "2010", "original_title": null, "ratings_count": "5", "ratings_sum": "16", "reviews_count": "9", "text_reviews_count": "2", "average_rating": null}}, {"id": "343486", "user_position": null, "series": {"id": "74376", "title": "Gateway Biography", "description": null, "note": null, "series_works_count": "18", "primary_work_count": "18", "numbered": "false"}, "work": {"id": "2079806", "best_book": {"id": "2074558", "title": "Laura Welch Bush: First Lady", "author": {"id": "75499", "name": "Tanya Lee Stone"}, "image_url": "https://s.gr-assets.com/assets/nophoto/book/111x148-bcc042a9c91a29c1d680899eff700a03.png"}, "books_count": "4", "original_publication_day": "1", "original_publication_month": "4", "original_publication_year": "2001", "original_title": "Laura Welch Bush: First Lady", "ratings_count": "10", "ratings_sum": "39", "reviews_count": "26", "text_reviews_count": "6", "average_rating": null}}, {"id": "256959", "user_position": null, "series": {"id": "60275", "title": "On My Own History", "description": null, "note": null, "series_works_count": "30", "primary_work_count": "30", "numbered": "false"}, "work": {"id": "594116", "best_book": {"id": "607604", "title": "Fire at the Triangle Factory (On My Own History)", "author": {"id": "190221", "name": "Holly Littlefield"}, "image_url": "https://s.gr-assets.com/assets/nophoto/book/111x148-bcc042a9c91a29c1d680899eff700a03.png"}, "books_count": "6", "original_publication_day": null, "original_publication_month": "4", "original_publication_year": "1995", "original_title": "Fire at the Triangle Factory (On My Own History)", "ratings_count": "35", "ratings_sum": "143", "reviews_count": "63", "text_reviews_count": "13", "average_rating": null}}, {"id": "409012", "user_position": null, "series": {"id": "85228", "title": "History Speaks: Picture Books Plus Reader's Theater", "description": "Bring to life important stories from U.S. history with the History Speaks: Picture Books Plus Reader\u2019s Theater. These books bring together illustrated picture books with readers's theater scripts for students to practice fluency", "note": null, "series_works_count": "12", "primary_work_count": "12", "numbered": "false"}, "work": {"id": "13815300", "best_book": {"id": "8938641", "title": "President Lincoln, Willie Kettles, and the Telegraph Machine", "author": {"id": "285029", "name": "Marty Rhodes Figley"}, "image_url": "https://s.gr-assets.com/assets/nophoto/book/111x148-bcc042a9c91a29c1d680899eff700a03.png"}, "books_count": "3", "original_publication_day": null, "original_publication_month": "8", "original_publication_year": "2010", "original_title": null, "ratings_count": "3", "ratings_sum": "14", "reviews_count": "3", "text_reviews_count": "0", "average_rating": null}}, {"id": "343492", "user_position": null, "series": {"id": "74376", "title": "Gateway Biography", "description": null, "note": null, "series_works_count": "18", "primary_work_count": "18", "numbered": "false"}, "work": {"id": "10615477", "best_book": {"id": "7757059", "title": "Michael Jackson: Ultimate Music Legend", "author": {"id": "3511", "name": "Katherine E. Krohn"}, "image_url": "https://s.gr-assets.com/assets/nophoto/book/111x148-bcc042a9c91a29c1d680899eff700a03.png"}, "books_count": "3", "original_publication_day": null, "original_publication_month": null, "original_publication_year": "2010", "original_title": null, "ratings_count": "28", "ratings_sum": "124", "reviews_count": "72", "text_reviews_count": "4", "average_rating": null}}, {"id": "256964", "user_position": null, "series": {"id": "60275", "title": "On My Own History", "description": null, "note": null, "series_works_count": "30", "primary_work_count": "30", "numbered": "false"}, "work": {"id": "881838", "best_book": {"id": "2288916", "title": "The Flight of the Union", "author": {"id": "460136", "name": "Tekla White"}, "image_url": "https://s.gr-assets.com/assets/nophoto/book/111x148-bcc042a9c91a29c1d680899eff700a03.png"}, "books_count": "3", "original_publication_day": null, "original_publication_month": "2", "original_publication_year": "1998", "original_title": "The Flight of the Union (On My Own History)", "ratings_count": "9", "ratings_sum": "36", "reviews_count": "15", "text_reviews_count": "1", "average_rating": null}}, {"id": "343493", "user_position": null, "series": {"id": "74376", "title": "Gateway Biography", "description": null, "note": null, "series_works_count": "18", "primary_work_count": "18", "numbered": "false"}, "work": {"id": "7248119", "best_book": {"id": "7003989", "title": "Michelle Obama", "author": {"id": "1490", "name": "Marlene Targ Brill"}, "image_url": "https://s.gr-assets.com/assets/nophoto/book/111x148-bcc042a9c91a29c1d680899eff700a03.png"}, "books_count": "2", "original_publication_day": null, "original_publication_month": null, "original_publication_year": "2008", "original_title": null, "ratings_count": "8", "ratings_sum": "32", "reviews_count": "14", "text_reviews_count": "2", "average_rating": null}}, {"id": "256965", "user_position": null, "series": {"id": "60275", "title": "On My Own History", "description": null, "note": null, "series_works_count": "30", "primary_work_count": "30", "numbered": "false"}, "work": {"id": "873305", "best_book": {"id": "888056", "title": "The Girl Who Struck Out Babe Ruth (On My Own History)", "author": {"id": "7231616", "name": "Jean L.S. Patrick"}, "image_url": "https://s.gr-assets.com/assets/nophoto/book/111x148-bcc042a9c91a29c1d680899eff700a03.png"}, "books_count": "10", "original_publication_day": "1", "original_publication_month": "1", "original_publication_year": "2000", "original_title": "The Girl Who Struck Out Babe Ruth (On My Own History)", "ratings_count": "33", "ratings_sum": "137", "reviews_count": "64", "text_reviews_count": "6", "average_rating": null}}, {"id": "343487", "user_position": null, "series": {"id": "74376", "title": "Gateway Biography", "description": null, "note": null, "series_works_count": "18", "primary_work_count": "18", "numbered": "false"}, "work": {"id": "771674", "best_book": {"id": "785676", "title": "Nancy Pelosi: First Woman Speaker of the House", "author": {"id": "60084", "name": "Lisa Tucker McElroy"}, "image_url": "https://s.gr-assets.com/assets/nophoto/book/111x148-bcc042a9c91a29c1d680899eff700a03.png"}, "books_count": "3", "original_publication_day": null, "original_publication_month": null, "original_publication_year": "2007", "original_title": "Nancy Pelosi: First Woman Speaker of the House (Gateway Biographies)", "ratings_count": "2", "ratings_sum": "7", "reviews_count": "4", "text_reviews_count": "1", "average_rating": null}}, {"id": "256967", "user_position": null, "series": {"id": "60275", "title": "On My Own History", "description": null, "note": null, "series_works_count": "30", "primary_work_count": "30", "numbered": "false"}, "work": {"id": "4800056", "best_book": {"id": "796891", "title": "I Pledge Allegiance", "author": {"id": "417591", "name": "June Swanson"}, "image_url": "https://s.gr-assets.com/assets/nophoto/book/111x148-bcc042a9c91a29c1d680899eff700a03.png"}, "books_count": "12", "original_publication_day": null, "original_publication_month": "3", "original_publication_year": "1990", "original_title": "I Pledge Allegiance (On My Own History)", "ratings_count": "16", "ratings_sum": "68", "reviews_count": "39", "text_reviews_count": "3", "average_rating": null}}, {"id": "343494", "user_position": null, "series": {"id": "74376", "title": "Gateway Biography", "description": null, "note": null, "series_works_count": "18", "primary_work_count": "18", "numbered": "false"}, "work": {"id": "16490978", "best_book": {"id": "11551005", "title": "Prince William & Kate: A Royal Romance", "author": {"id": "48437", "name": "Matt Doeden"}, "image_url": "https://d.gr-assets.com/books/1308604668m/11551005.jpg"}, "books_count": "4", "original_publication_day": "1", "original_publication_month": "9", "original_publication_year": "2011", "original_title": null, "ratings_count": "51", "ratings_sum": "182", "reviews_count": "117", "text_reviews_count": "17", "average_rating": null}}, {"id": "256973", "user_position": null, "series": {"id": "60275", "title": "On My Own History", "description": null, "note": null, "series_works_count": "30", "primary_work_count": "30", "numbered": "false"}, "work": {"id": "206027", "best_book": {"id": "212834", "title": "Kate Shelley and the Midnight Express (On My Own History)", "author": {"id": "124782", "name": "Margaret K. Wetterer"}, "image_url": "https://s.gr-assets.com/assets/nophoto/book/111x148-bcc042a9c91a29c1d680899eff700a03.png"}, "books_count": "19", "original_publication_day": "1", "original_publication_month": "1", "original_publication_year": "1990", "original_title": "Kate Shelley and the Midnight Express (On My Own History)", "ratings_count": "94", "ratings_sum": "394", "reviews_count": "219", "text_reviews_count": "22", "average_rating": null}}, {"id": "343495", "user_position": null, "series": {"id": "74376", "title": "Gateway Biography", "description": null, "note": null, "series_works_count": "18", "primary_work_count": "18", "numbered": "false"}, "work": {"id": "11623289", "best_book": {"id": "7955106", "title": "Sonia Sotomayor: First Hispanic U.S. Supreme Court Justice", "author": {"id": "60084", "name": "Lisa Tucker McElroy"}, "image_url": "https://s.gr-assets.com/assets/nophoto/book/111x148-bcc042a9c91a29c1d680899eff700a03.png"}, "books_count": "2", "original_publication_day": null, "original_publication_month": "4", "original_publication_year": "2010", "original_title": null, "ratings_count": "0", "ratings_sum": "0", "reviews_count": "5", "text_reviews_count": "1", "average_rating": null}}, {"id": "256975", "user_position": null, "series": {"id": "60275", "title": "On My Own History", "description": null, "note": null, "series_works_count": "30", "primary_work_count": "30", "numbered": "false"}, "work": {"id": "1170430", "best_book": {"id": "1182507", "title": "Keep the Lights Burning, Abbie (On My Own History)", "author": {"id": "2692", "name": "Peter Roop"}, "image_url": "https://s.gr-assets.com/assets/nophoto/book/111x148-bcc042a9c91a29c1d680899eff700a03.png"}, "books_count": "21", "original_publication_day": null, "original_publication_month": null, "original_publication_year": "1985", "original_title": "Keep the Lights Burning, Abbie (On My Own History)", "ratings_count": "480", "ratings_sum": "1934", "reviews_count": "866", "text_reviews_count": "39", "average_rating": null}}, {"id": "343496", "user_position": null, "series": {"id": "74376", "title": "Gateway Biography", "description": null, "note": null, "series_works_count": "18", "primary_work_count": "18", "numbered": "false"}, "work": {"id": "6273410", "best_book": {"id": "6096318", "title": "Ted Kennedy: A Remarkable Life in the Senate", "author": {"id": "60084", "name": "Lisa Tucker McElroy"}, "image_url": "https://s.gr-assets.com/assets/nophoto/book/111x148-bcc042a9c91a29c1d680899eff700a03.png"}, "books_count": "1", "original_publication_day": null, "original_publication_month": "4", "original_publication_year": "2009", "original_title": "Ted Kennedy: A Remarkable Life in the Senate (Gateway Biographies)", "ratings_count": "2", "ratings_sum": "8", "reviews_count": "4", "text_reviews_count": "0", "average_rating": null}}, {"id": "354796", "user_position": null, "series": {"id": "60275", "title": "On My Own History", "description": null, "note": null, "series_works_count": "30", "primary_work_count": "30", "numbered": "false"}, "work": {"id": "9744781", "best_book": {"id": "7521870", "title": "Many Ways to Be a Soldier", "author": {"id": "79354", "name": "Wendy Pfeffer"}, "image_url": "https://s.gr-assets.com/assets/nophoto/book/111x148-bcc042a9c91a29c1d680899eff700a03.png"}, "books_count": "4", "original_publication_day": null, "original_publication_month": null, "original_publication_year": "2007", "original_title": null, "ratings_count": "5", "ratings_sum": "19", "reviews_count": "12", "text_reviews_count": "2", "average_rating": null}}, {"id": "343488", "user_position": null, "series": {"id": "74376", "title": "Gateway Biography", "description": null, "note": null, "series_works_count": "18", "primary_work_count": "18", "numbered": "false"}, "work": {"id": "37285", "best_book": {"id": "37410", "title": "Toni Morrison", "author": {"id": "102470", "name": "James Haskins"}, "image_url": "https://s.gr-assets.com/assets/nophoto/book/111x148-bcc042a9c91a29c1d680899eff700a03.png"}, "books_count": "2", "original_publication_day": null, "original_publication_month": null, "original_publication_year": "2001", "original_title": "Toni Morrison: Magic Of Words (Gateway Biographies)", "ratings_count": "1", "ratings_sum": "5", "reviews_count": "7", "text_reviews_count": "0", "average_rating": null}}, {"id": "354797", "user_position": null, "series": {"id": "60275", "title": "On My Own History", "description": null, "note": null, "series_works_count": "30", "primary_work_count": "30", "numbered": "false"}, "work": {"id": "5434402", "best_book": {"id": "5366888", "title": "The Night of the Hurricane's Fury", "author": {"id": "5353829", "name": "Candice Ransom"}, "image_url": "https://s.gr-assets.com/assets/nophoto/book/111x148-bcc042a9c91a29c1d680899eff700a03.png"}, "books_count": "2", "original_publication_day": null, "original_publication_month": "2", "original_publication_year": "2009", "original_title": "The Night of the Hurricane's Fury (On My Own History)", "ratings_count": "1", "ratings_sum": "4", "reviews_count": "7", "text_reviews_count": "1", "average_rating": null}}, {"id": "343497", "user_position": null, "series": {"id": "74376", "title": "Gateway Biography", "description": null, "note": null, "series_works_count": "18", "primary_work_count": "18", "numbered": "false"}, "work": {"id": "7315981", "best_book": {"id": "7063661", "title": "Tyra Banks: From Supermodel to Role Model", "author": {"id": "125486", "name": "Anne E. Hill"}, "image_url": "https://s.gr-assets.com/assets/nophoto/book/111x148-bcc042a9c91a29c1d680899eff700a03.png"}, "books_count": "1", "original_publication_day": null, "original_publication_month": null, "original_publication_year": "2009", "original_title": null, "ratings_count": "2", "ratings_sum": "10", "reviews_count": "8", "text_reviews_count": "0", "average_rating": null}}, {"id": "354798", "user_position": null, "series": {"id": "60275", "title": "On My Own History", "description": null, "note": null, "series_works_count": "30", "primary_work_count": "30", "numbered": "false"}, "work": {"id": "5401540", "best_book": {"id": "5334054", "title": "Prisoner for Liberty", "author": {"id": "285029", "name": "Marty Rhodes Figley"}, "image_url": "https://s.gr-assets.com/assets/nophoto/book/111x148-bcc042a9c91a29c1d680899eff700a03.png"}, "books_count": "4", "original_publication_day": "15", "original_publication_month": "12", "original_publication_year": "2007", "original_title": "Prisoner for Liberty (On My Own History)", "ratings_count": "6", "ratings_sum": "25", "reviews_count": "17", "text_reviews_count": "1", "average_rating": null}}, {"id": "256976", "user_position": null, "series": {"id": "60275", "title": "On My Own History", "description": null, "note": null, "series_works_count": "30", "primary_work_count": "30", "numbered": "false"}, "work": {"id": "4420769", "best_book": {"id": "4372758", "title": "Rescue on the Outer Banks (On My Own History)", "author": {"id": "5353829", "name": "Candice Ransom"}, "image_url": "https://s.gr-assets.com/assets/nophoto/book/111x148-bcc042a9c91a29c1d680899eff700a03.png"}, "books_count": "6", "original_publication_day": "1", "original_publication_month": "1", "original_publication_year": "2002", "original_title": "Rescue on the Outer Banks", "ratings_count": "13", "ratings_sum": "51", "reviews_count": "27", "text_reviews_count": "5", "average_rating": null}}, {"id": "256978", "user_position": null, "series": {"id": "60275", "title": "On My Own History", "description": null, "note": null, "series_works_count": "30", "primary_work_count": "30", "numbered": "false"}, "work": {"id": "881840", "best_book": {"id": "896649", "title": "Robert Smalls Sails to Freedom", "author": {"id": "137836", "name": "Susan Taylor Brown"}, "image_url": "https://s.gr-assets.com/assets/nophoto/book/111x148-bcc042a9c91a29c1d680899eff700a03.png"}, "books_count": "3", "original_publication_day": "28", "original_publication_month": "1", "original_publication_year": "2006", "original_title": "Robert Smalls Sails to Freedom (On My Own History)", "ratings_count": "6", "ratings_sum": "23", "reviews_count": "17", "text_reviews_count": "0", "average_rating": null}}, {"id": "256980", "user_position": null, "series": {"id": "60275", "title": "On My Own History", "description": null, "note": null, "series_works_count": "30", "primary_work_count": "30", "numbered": "false"}, "work": {"id": "446903", "best_book": {"id": "458410", "title": "Sam Collier and the Founding of Jamestown (On My Own History)", "author": {"id": "5353829", "name": "Candice Ransom"}, "image_url": "https://s.gr-assets.com/assets/nophoto/book/111x148-bcc042a9c91a29c1d680899eff700a03.png"}, "books_count": "3", "original_publication_day": "31", "original_publication_month": "10", "original_publication_year": "2005", "original_title": "Sam Collier and the Founding of Jamestown (On My Own History)", "ratings_count": "4", "ratings_sum": "14", "reviews_count": "11", "text_reviews_count": "0", "average_rating": null}}, {"id": "256981", "user_position": null, "series": {"id": "60275", "title": "On My Own History", "description": null, "note": null, "series_works_count": "30", "primary_work_count": "30", "numbered": "false"}, "work": {"id": "5138930", "best_book": {"id": "2581575", "title": "Saving the Liberty Bell", "author": {"id": "285029", "name": "Marty Rhodes Figley"}, "image_url": "https://d.gr-assets.com/books/1331509310m/2581575.jpg"}, "books_count": "8", "original_publication_day": null, "original_publication_month": "9", "original_publication_year": "2004", "original_title": "Saving the Liberty Bell", "ratings_count": "1", "ratings_sum": "5", "reviews_count": "16", "text_reviews_count": "1", "average_rating": null}}, {"id": "256983", "user_position": null, "series": {"id": "60275", "title": "On My Own History", "description": null, "note": null, "series_works_count": "30", "primary_work_count": "30", "numbered": "false"}, "work": {"id": "1361361", "best_book": {"id": "1371501", "title": "The Schoolchildren's Blizzard", "author": {"id": "285029", "name": "Marty Rhodes Figley"}, "image_url": "https://s.gr-assets.com/assets/nophoto/book/111x148-bcc042a9c91a29c1d680899eff700a03.png"}, "books_count": "5", "original_publication_day": "1", "original_publication_month": "1", "original_publication_year": "2004", "original_title": "The Schoolchildren's Blizzard (On My Own History)", "ratings_count": "22", "ratings_sum": "88", "reviews_count": "46", "text_reviews_count": "3", "average_rating": null}}, {"id": "256985", "user_position": null, "series": {"id": "60275", "title": "On My Own History", "description": null, "note": null, "series_works_count": "30", "primary_work_count": "30", "numbered": "false"}, "work": {"id": "1462541", "best_book": {"id": "1471574", "title": "The Snow Walker", "author": {"id": "124782", "name": "Margaret K. Wetterer"}, "image_url": "https://s.gr-assets.com/assets/nophoto/book/111x148-bcc042a9c91a29c1d680899eff700a03.png"}, "books_count": "12", "original_publication_day": "1", "original_publication_month": "12", "original_publication_year": "1995", "original_title": "The Snow Walker (On My Own History)", "ratings_count": "30", "ratings_sum": "118", "reviews_count": "60", "text_reviews_count": "3", "average_rating": null}}, {"id": "256987", "user_position": null, "series": {"id": "60275", "title": "On My Own History", "description": null, "note": null, "series_works_count": "30", "primary_work_count": "30", "numbered": "false"}, "work": {"id": "1348039", "best_book": {"id": "3991102", "title": "The Star-Spangled Banner", "author": {"id": "119012", "name": "Catherine A. Welch"}, "image_url": "https://d.gr-assets.com/books/1331509390m/3991102.jpg"}, "books_count": "6", "original_publication_day": null, "original_publication_month": null, "original_publication_year": "2004", "original_title": "The Star-Spangled Banner", "ratings_count": "0", "ratings_sum": "0", "reviews_count": "6", "text_reviews_count": "0", "average_rating": null}}, {"id": "256988", "user_position": null, "series": {"id": "60275", "title": "On My Own History", "description": null, "note": null, "series_works_count": "30", "primary_work_count": "30", "numbered": "false"}, "work": {"id": "287845", "best_book": {"id": "296655", "title": "Sybil Ludington's Midnight Ride (On My Own History)", "author": {"id": "171243", "name": "Marsha Amstel"}, "image_url": "https://s.gr-assets.com/assets/nophoto/book/111x148-bcc042a9c91a29c1d680899eff700a03.png"}, "books_count": "6", "original_publication_day": "1", "original_publication_month": "9", "original_publication_year": "2000", "original_title": "Sybil Ludington's Midnight Ride (On My Own History)", "ratings_count": "35", "ratings_sum": "136", "reviews_count": "102", "text_reviews_count": "6", "average_rating": null}}, {"id": "256946", "user_position": null, "series": {"id": "60275", "title": "On My Own History", "description": null, "note": null, "series_works_count": "30", "primary_work_count": "30", "numbered": "false"}, "work": {"id": "2597255", "best_book": {"id": "2581574", "title": "Washington Is Burning", "author": {"id": "285029", "name": "Marty Rhodes Figley"}, "image_url": "https://s.gr-assets.com/assets/nophoto/book/111x148-bcc042a9c91a29c1d680899eff700a03.png"}, "books_count": "3", "original_publication_day": "15", "original_publication_month": "12", "original_publication_year": "2005", "original_title": "Washington Is Burning (On My Own History)", "ratings_count": "6", "ratings_sum": "24", "reviews_count": "15", "text_reviews_count": "1", "average_rating": null}}, {"id": "256990", "user_position": null, "series": {"id": "60275", "title": "On My Own History", "description": null, "note": null, "series_works_count": "30", "primary_work_count": "30", "numbered": "false"}, "work": {"id": "6102082", "best_book": {"id": "5929639", "title": "Will and Orv (On My Own History)", "author": {"id": "1130197", "name": "Walter A. Schulz"}, "image_url": "https://s.gr-assets.com/assets/nophoto/book/111x148-bcc042a9c91a29c1d680899eff700a03.png"}, "books_count": "9", "original_publication_day": "1", "original_publication_month": "8", "original_publication_year": "1991", "original_title": "Will and Orv (On My Own History)", "ratings_count": "7", "ratings_sum": "25", "reviews_count": "32", "text_reviews_count": "1", "average_rating": null}}, {"id": "256991", "user_position": null, "series": {"id": "60275", "title": "On My Own History", "description": null, "note": null, "series_works_count": "30", "primary_work_count": "30", "numbered": "false"}, "work": {"id": "463628", "best_book": {"id": "1024176", "title": "Willie McLean and the Civil War Surrender (On My Own History)", "author": {"id": "5353829", "name": "Candice Ransom"}, "image_url": "https://s.gr-assets.com/assets/nophoto/book/111x148-bcc042a9c91a29c1d680899eff700a03.png"}, "books_count": "3", "original_publication_day": null, "original_publication_month": "9", "original_publication_year": "2004", "original_title": "Willie McLean and the Civil War Surrender (On My Own History)", "ratings_count": "4", "ratings_sum": "16", "reviews_count": "15", "text_reviews_count": "1", "average_rating": null}}]}}}