{
  "last_modified": "2016-04-28T11:03:27-04:00",
  "results": {
    "updated": "WEEKLY",
    "list_name": "Combined Print and E-Book Fiction",
    "published_date": "2014-09-21",
    "books": [
      {
        "price": 0,
        "primary_isbn10": "0804178763",
        "asterisk": 0,
        "dagger": 0,
        "author": "Lee Child",
        "primary_isbn13": "9780804178761",
        "description": "Jack Reacher, a former military cop, helps the State Department and the C.I.A. stop a sniper who has targeted a G8 summit.\u00a0",
        "book_review_link": "",
        "book_image_height": 194,
        "book_image": "https://s1.nyt.com/du/books/images/9780804178747.jpg",
        "rank": 1,
        "article_chapter_link": "",
        "rank_last_week": 0,
        "book_image_width": 128,
        "first_chapter_link": "",
        "age_group": "",
        "weeks_on_list": 1,
        "amazon_product_url": "http://www.amazon.com/Personal-Jack-Reacher-Lee-Child/dp/0804178747?tag=thenewyorktim-20",
        "contributor": "by Lee Child",
        "title": "PERSONAL",
        "sunday_review_link": "",
        "contributor_note": "",
        "isbns": [
          {
            "isbn10": "0804178747",
            "isbn13": "9780804178747"
          },
          {
            "isbn10": "0804178763",
            "isbn13": "9780804178761"
          },
          {
            "isbn10": "1473508770",
            "isbn13": "9781473508774"
          },
          {
            "isbn10": "0804178755",
            "isbn13": "9780804178754"
          }
        ],
        "publisher": "Delacorte"
      },
      {
        "price": 0,
        "primary_isbn10": "0399167447",
        "asterisk": 0,
        "dagger": 0,
        "author": "Jan Karon",
        "primary_isbn13": "9780399167447",
        "description": "The Mitford character Father Tim Kavanagh returns to his native town to find friends and family wrestling with difficulties.\u00a0",
        "book_review_link": "",
        "book_image_height": 193,
        "book_image": "https://s1.nyt.com/du/books/images/9780399167447.jpg",
        "rank": 2,
        "article_chapter_link": "",
        "rank_last_week": 0,
        "book_image_width": 128,
        "first_chapter_link": "",
        "age_group": "",
        "weeks_on_list": 1,
        "amazon_product_url": "http://www.amazon.com/Somewhere-Safe-Somebody-Good-Mitford/dp/0399167447?tag=thenewyorktim-20",
        "contributor": "by Jan Karon",
        "title": "SOMEWHERE SAFE WITH SOMEBODY GOOD",
        "sunday_review_link": "",
        "contributor_note": "",
        "isbns": [
          {
            "isbn10": "0399167447",
            "isbn13": "9780399167447"
          },
          {
            "isbn10": "0698141407",
            "isbn13": "9780698141407"
          },
          {
            "isbn10": "042527621X",
            "isbn13": "9780425276211"
          }
        ],
        "publisher": "Putnam"
      },
      {
        "price": 0,
        "primary_isbn10": "",
        "asterisk": 0,
        "dagger": 0,
        "author": "Clive Cussler and Russell Blake",
        "primary_isbn13": "9780698140745",
        "description": "The treasure hunters Sam and Remi Fargo discover a Viking ship in the Arctic ice, full of artifacts from pre-Columbian Mexico.",
        "book_review_link": "",
        "book_image_height": 194,
        "book_image": "https://s1.nyt.com/du/books/images/9780698140745.jpg",
        "rank": 3,
        "article_chapter_link": "",
        "rank_last_week": 0,
        "book_image_width": 128,
        "first_chapter_link": "",
        "age_group": "",
        "weeks_on_list": 1,
        "amazon_product_url": "http://www.amazon.com/The-Eye-Heaven-Fargo-Adventure-ebook/dp/B00INIXHLU?tag=thenewyorktim-20",
        "contributor": "by Clive Cussler and Russell Blake",
        "title": "THE EYE OF HEAVEN",
        "sunday_review_link": "",
        "contributor_note": "",
        "isbns": [
          {
            "isbn10": "0399167307",
            "isbn13": "9780399167300"
          },
          {
            "isbn10": "0425275175",
            "isbn13": "9780425275177"
          }
        ],
        "publisher": "Putnam"
      },
      {
        "price": 0,
        "primary_isbn10": "0307588386",
        "asterisk": 0,
        "dagger": 0,
        "author": "Gillian Flynn",
        "primary_isbn13": "9780307588388",
        "description": "A woman disappears on the day of her fifth anniversary; is her husband a killer?",
        "book_review_link": "//www.nytimes.com/2012/05/30/books/gone-girl-by-gillian-flynn.html",
        "book_image_height": 200,
        "book_image": "https://s1.nyt.com/du/books/images/9780307588388.jpg",
        "rank": 4,
        "article_chapter_link": "",
        "rank_last_week": 4,
        "book_image_width": 136,
        "first_chapter_link": "",
        "age_group": "",
        "weeks_on_list": 93,
        "amazon_product_url": "http://www.amazon.com/Gone-Girl-Novel-Gillian-Flynn-ebook/dp/B006LSZECO?tag=thenewyorktim-20",
        "contributor": "by Gillian Flynn",
        "title": "GONE GIRL",
        "sunday_review_link": "//www.nytimes.com/2012/06/17/books/review/gillian-flynns-gone-girl-and-more.html",
        "contributor_note": "",
        "isbns": [
          {
            "isbn10": "030758836X",
            "isbn13": "9780307588364"
          },
          {
            "isbn10": "0307588386",
            "isbn13": "9780307588388"
          },
          {
            "isbn10": "1410450953",
            "isbn13": "9781410450951"
          },
          {
            "isbn10": "0297859382",
            "isbn13": "9780297859383"
          },
          {
            "isbn10": "0307588378",
            "isbn13": "9780307588371"
          },
          {
            "isbn10": "0297859390",
            "isbn13": "9780297859390"
          },
          {
            "isbn10": "159413605X",
            "isbn13": "9781594136054"
          },
          {
            "isbn10": "055341836X",
            "isbn13": "9780553418361"
          },
          {
            "isbn10": "0553418351",
            "isbn13": "9780553418354"
          },
          {
            "isbn10": "0606270175",
            "isbn13": "9780606270175"
          }
        ],
        "publisher": "Crown"
      },
      {
        "price": 0,
        "primary_isbn10": "",
        "asterisk": 0,
        "dagger": 0,
        "author": "Tana French",
        "primary_isbn13": "9780698170285",
        "description": "A clue to a murder on the grounds of a girls\u2019 school in the Dublin suburbs appears on a bulletin board, and Detectives Stephen Moran and Antoinette Conway investigate.\u00a0",
        "book_review_link": "//www.nytimes.com/2014/08/26/books/tana-frenchs-the-secret-place-involves-a-girls-school.html",
        "book_image_height": 193,
        "book_image": "https://s1.nyt.com/du/books/images/9780698170285.jpg",
        "rank": 5,
        "article_chapter_link": "",
        "rank_last_week": 0,
        "book_image_width": 128,
        "first_chapter_link": "",
        "age_group": "",
        "weeks_on_list": 1,
        "amazon_product_url": "http://www.amazon.com/Secret-Place-Dublin-Murder-Squad/dp/0670026328?tag=thenewyorktim-20",
        "contributor": "by Tana French",
        "title": "THE SECRET PLACE",
        "sunday_review_link": "",
        "contributor_note": "",
        "isbns": [
          {
            "isbn10": "0670026328",
            "isbn13": "9780670026326"
          }
        ],
        "publisher": "Viking"
      },
      {
        "price": 0,
        "primary_isbn10": "0440335167",
        "asterisk": 0,
        "dagger": 0,
        "author": "Diana Gabaldon",
        "primary_isbn13": "9780440335160",
        "description": "Claire Randall, an English nurse, is transported back to 1743 during a second honeymoon in the Scottish Highlands. There she begins an affair with James Fraser, a redheaded soldier. Originally published in 1991.",
        "book_review_link": "",
        "book_image_height": 500,
        "book_image": "https://s1.nyt.com/du/books/images/9780440212560.jpg",
        "rank": 6,
        "article_chapter_link": "",
        "rank_last_week": 7,
        "book_image_width": 304,
        "first_chapter_link": "",
        "age_group": "",
        "weeks_on_list": 6,
        "amazon_product_url": "http://www.amazon.com/Outlander-Diana-Gabaldon/dp/0440212561?tag=thenewyorktim-20",
        "contributor": "by Diana Gabaldon",
        "title": "OUTLANDER",
        "sunday_review_link": "",
        "contributor_note": "",
        "isbns": [
          {
            "isbn10": "0440335167",
            "isbn13": "9780440335160"
          },
          {
            "isbn10": "0440212561",
            "isbn13": "9780440212560"
          },
          {
            "isbn10": "0385319959",
            "isbn13": "9780385319959"
          },
          {
            "isbn10": "0553393693",
            "isbn13": "9780553393699"
          },
          {
            "isbn10": "0553393707",
            "isbn13": "9780553393705"
          },
          {
            "isbn10": "0440423201",
            "isbn13": "9780440423201"
          },
          {
            "isbn10": "0385302304",
            "isbn13": "9780385302302"
          }
        ],
        "publisher": "Dell"
      },
      {
        "price": 0,
        "primary_isbn10": "None",
        "asterisk": 0,
        "dagger": 0,
        "author": "Sandra Brown",
        "primary_isbn13": "9781455581139",
        "description": "A North Carolina pediatrician is held captive by a mysterious man who forces her to question her life.",
        "book_review_link": "",
        "book_image_height": 193,
        "book_image": "https://s1.nyt.com/du/books/images/9781455581139.jpg",
        "rank": 7,
        "article_chapter_link": "",
        "rank_last_week": 8,
        "book_image_width": 128,
        "first_chapter_link": "",
        "age_group": "",
        "weeks_on_list": 3,
        "amazon_product_url": "http://www.amazon.com/Mean-Streak-Sandra-Brown/dp/1455581127?tag=thenewyorktim-20",
        "contributor": "by Sandra Brown",
        "title": "MEAN STREAK",
        "sunday_review_link": "",
        "contributor_note": "",
        "isbns": [
          {
            "isbn10": "1455581127",
            "isbn13": "9781455581122"
          },
          {
            "isbn10": "1455530085",
            "isbn13": "9781455530083"
          },
          {
            "isbn10": "1455559121",
            "isbn13": "9781455559121"
          },
          {
            "isbn10": "1455581143",
            "isbn13": "9781455581146"
          },
          {
            "isbn10": "1455581151",
            "isbn13": "9781455581153"
          }
        ],
        "publisher": "Grand Central"
      },
      {
        "price": 0,
        "primary_isbn10": "",
        "asterisk": 0,
        "dagger": 0,
        "author": "Christine Feehan",
        "primary_isbn13": "9780698139350",
        "description": "In Book 26 (and part of a sub-trilogy) of the Dark series, Zev, an elite warrior, wonders about the future of the Carpathians.",
        "book_review_link": "",
        "book_image_height": 500,
        "book_image": "https://s1.nyt.com/du/books/images/9780698139350.jpg",
        "rank": 8,
        "article_chapter_link": "",
        "rank_last_week": 0,
        "book_image_width": 331,
        "first_chapter_link": "",
        "age_group": "",
        "weeks_on_list": 1,
        "amazon_product_url": "http://www.amazon.com/Dark-Blood-Carpathian-Christine-Feehan/dp/0425271447?tag=thenewyorktim-20",
        "contributor": "by Christine Feehan",
        "title": "DARK BLOOD",
        "sunday_review_link": "",
        "contributor_note": "",
        "isbns": [
          {
            "isbn10": "0425271447",
            "isbn13": "9780425271445"
          }
        ],
        "publisher": "Berkley"
      },
      {
        "price": 0,
        "primary_isbn10": "0698138635",
        "asterisk": 0,
        "dagger": 0,
        "author": "Liane Moriarty",
        "primary_isbn13": "9780698138636",
        "description": "Who will end up dead, and how, when three mothers with children in the same school become friends?",
        "book_review_link": "//www.nytimes.com/2014/07/25/books/in-big-little-lies-liane-moriarty-finds-new-complications.html",
        "book_image_height": 193,
        "book_image": "https://s1.nyt.com/du/books/images/9780698138636.jpg",
        "rank": 9,
        "article_chapter_link": "",
        "rank_last_week": 5,
        "book_image_width": 128,
        "first_chapter_link": "",
        "age_group": "",
        "weeks_on_list": 6,
        "amazon_product_url": "http://www.amazon.com/Big-Little-Lies-Liane-Moriarty-ebook/dp/B00HDMMISA?tag=thenewyorktim-20",
        "contributor": "by Liane Moriarty",
        "title": "BIG LITTLE LIES",
        "sunday_review_link": "",
        "contributor_note": "",
        "isbns": [
          {
            "isbn10": "0399167064",
            "isbn13": "9780399167065"
          },
          {
            "isbn10": "0698138635",
            "isbn13": "9780698138636"
          },
          {
            "isbn10": "1410472035",
            "isbn13": "9781410472038"
          },
          {
            "isbn10": "0425274861",
            "isbn13": "9780425274866"
          },
          {
            "isbn10": "1594139067",
            "isbn13": "9781594139062"
          }
        ],
        "publisher": "Amy Einhorn/Putnam"
      },
      {
        "price": 0,
        "primary_isbn10": "1400065674",
        "asterisk": 0,
        "dagger": 0,
        "author": "David Mitchell",
        "primary_isbn13": "9781400065677",
        "description": "Stories from the medieval Swiss Alps to the 19th-century Australian bush to a hotel in Shanghai to Manhattan in the near future are stitched together.\u00a0",
        "book_review_link": "//www.nytimes.com/2014/08/27/books/david-mitchells-the-bone-clocks-explores-a-girls-journey.html",
        "book_image_height": 191,
        "book_image": "https://s1.nyt.com/du/books/images/9781400065677.jpg",
        "rank": 10,
        "article_chapter_link": "",
        "rank_last_week": 0,
        "book_image_width": 128,
        "first_chapter_link": "",
        "age_group": "",
        "weeks_on_list": 1,
        "amazon_product_url": "http://www.amazon.com/The-Bone-Clocks-A-Novel-ebook/dp/B00IHMF9KE?tag=thenewyorktim-20",
        "contributor": "by David Mitchell",
        "title": "THE BONE CLOCKS",
        "sunday_review_link": "//www.nytimes.com/2014/08/31/books/review/the-bone-clocks-by-david-mitchell.html",
        "contributor_note": "",
        "isbns": [
          {
            "isbn10": "1400065674",
            "isbn13": "9781400065677"
          },
          {
            "isbn10": "0812994736",
            "isbn13": "9780812994735"
          }
        ],
        "publisher": "Random House"
      },
      {
        "price": 0,
        "primary_isbn10": "",
        "asterisk": 0,
        "dagger": 0,
        "author": "Abbi Glines",
        "primary_isbn13": "9781476756592",
        "description": "The story of Grant and Harlow continues; Book 7 in the Rosemary Beach series.",
        "book_review_link": "",
        "book_image_height": 198,
        "book_image": "https://s1.nyt.com/du/books/images/9781476756592.jpg",
        "rank": 11,
        "article_chapter_link": "",
        "rank_last_week": 0,
        "book_image_width": 128,
        "first_chapter_link": "",
        "age_group": "",
        "weeks_on_list": 1,
        "amazon_product_url": "http://www.amazon.com/One-More-Chance-Rosemary-Beach-ebook/dp/B00GEEB4EM?tag=thenewyorktim-20",
        "contributor": "by Abbi Glines",
        "title": "ONE MORE CHANCE",
        "sunday_review_link": "",
        "contributor_note": "",
        "isbns": [
          {
            "isbn10": "1476756570",
            "isbn13": "9781476756578"
          }
        ],
        "publisher": "Atria"
      },
      {
        "price": 0,
        "primary_isbn10": "",
        "asterisk": 0,
        "dagger": 0,
        "author": "Sherrilyn Kenyon",
        "primary_isbn13": "9781250029928",
        "description": "Book 18 of the Dark-Hunter novels finds Cadegan, who has been damned for centuries, in pursuit of Josette Landry.\u00a0",
        "book_review_link": "",
        "book_image_height": 191,
        "book_image": "https://s1.nyt.com/du/books/images/9781250029928.jpg",
        "rank": 12,
        "article_chapter_link": "",
        "rank_last_week": 0,
        "book_image_width": 128,
        "first_chapter_link": "",
        "age_group": "",
        "weeks_on_list": 1,
        "amazon_product_url": "http://www.amazon.com/Son-No-One-Dark-Hunter-Novels/dp/1250029910?tag=thenewyorktim-20",
        "contributor": "by Sherrilyn Kenyon",
        "title": "SON OF NO ONE",
        "sunday_review_link": "",
        "contributor_note": "",
        "isbns": [
          {
            "isbn10": "1250029910",
            "isbn13": "9781250029911"
          }
        ],
        "publisher": "St. Martin's"
      },
      {
        "price": 0,
        "primary_isbn10": "1420134965",
        "asterisk": 0,
        "dagger": 0,
        "author": "Fern Michaels",
        "primary_isbn13": "9781420134964",
        "description": "The men in the Sisterhood\u2019s lives join forces to see justice served.",
        "book_review_link": "",
        "book_image_height": 192,
        "book_image": "https://s1.nyt.com/du/books/images/9781420134964.jpg",
        "rank": 13,
        "article_chapter_link": "",
        "rank_last_week": 0,
        "book_image_width": 128,
        "first_chapter_link": "",
        "age_group": "",
        "weeks_on_list": 1,
        "amazon_product_url": "http://www.amazon.com/Countdown-The-Sisterhood-Fern-Michaels-ebook/dp/B00JFABVXG?tag=thenewyorktim-20",
        "contributor": "by Fern Michaels",
        "title": "COUNTDOWN",
        "sunday_review_link": "",
        "contributor_note": "",
        "isbns": [
          {
            "isbn10": "1420134965",
            "isbn13": "9781420134964"
          }
        ],
        "publisher": "Kensington"
      },
      {
        "price": 0,
        "primary_isbn10": "1455556564",
        "asterisk": 0,
        "dagger": 0,
        "author": "Nicholas Sparks",
        "primary_isbn13": "9781455556564",
        "description": "Twenty-five years after their high school romance ended, a man and woman who have gone their separate ways return to their North Carolina town for the funeral of a friend.",
        "book_review_link": "",
        "book_image_height": 280,
        "book_image": "https://s1.nyt.com/du/books/images/9780446547642.jpg",
        "rank": 14,
        "article_chapter_link": "",
        "rank_last_week": 0,
        "book_image_width": 185,
        "first_chapter_link": "",
        "age_group": "",
        "weeks_on_list": 2,
        "amazon_product_url": "http://www.amazon.com/The-Best-Me-Nicholas-Sparks/dp/0446547646?tag=thenewyorktim-20",
        "contributor": "by Nicholas Sparks",
        "title": "THE BEST OF ME",
        "sunday_review_link": "",
        "contributor_note": "",
        "isbns": [
          {
            "isbn10": "0446547654",
            "isbn13": "9780446547659"
          },
          {
            "isbn10": "0446547646",
            "isbn13": "9780446547642"
          },
          {
            "isbn10": "1455504106",
            "isbn13": "9781455504107"
          },
          {
            "isbn10": "0446547638",
            "isbn13": "9780446547635"
          },
          {
            "isbn10": "1455556556",
            "isbn13": "9781455556557"
          },
          {
            "isbn10": "1455556564",
            "isbn13": "9781455556564"
          }
        ],
        "publisher": "Grand Central"
      },
      {
        "price": 0,
        "primary_isbn10": "0345543246",
        "asterisk": 0,
        "dagger": 0,
        "author": "John Grisham",
        "primary_isbn13": "9780345543240",
        "description": "A sequel, about race and inheritance, to \u201cA Time to Kill.\u201d",
        "book_review_link": "//www.nytimes.com/2013/10/31/books/sycamore-row-by-john-grisham.html",
        "book_image_height": 500,
        "book_image": "https://s1.nyt.com/du/books/images/9780385537926.jpg",
        "rank": 15,
        "article_chapter_link": "",
        "rank_last_week": 9,
        "book_image_width": 329,
        "first_chapter_link": "",
        "age_group": "",
        "weeks_on_list": 26,
        "amazon_product_url": "http://www.amazon.com/Sycamore-Jake-Brigance-John-Grisham/dp/0385537131?tag=thenewyorktim-20",
        "contributor": "by John Grisham",
        "title": "SYCAMORE ROW",
        "sunday_review_link": "//www.nytimes.com/2013/11/10/books/review/sycamore-row-by-john-grisham.html",
        "contributor_note": "",
        "isbns": [
          {
            "isbn10": "0385537131",
            "isbn13": "9780385537131"
          },
          {
            "isbn10": "0385537921",
            "isbn13": "9780385537926"
          },
          {
            "isbn10": "0553393618",
            "isbn13": "9780553393613"
          },
          {
            "isbn10": "0345543246",
            "isbn13": "9780345543240"
          }
        ],
        "publisher": "Doubleday"
      },
      {
        "price": 0,
        "primary_isbn10": "",
        "asterisk": 0,
        "dagger": 0,
        "author": "Faye Kellerman",
        "primary_isbn13": "9780062270207",
        "description": "",
        "book_review_link": "",
        "book_image_height": 183,
        "book_image": "https://s1.nyt.com/du/books/images/9780062270207.jpg",
        "rank": 16,
        "article_chapter_link": "",
        "rank_last_week": 0,
        "book_image_width": 128,
        "first_chapter_link": "",
        "age_group": "",
        "weeks_on_list": 0,
        "amazon_product_url": "http://www.amazon.com/Murder-101-Decker-Lazarus-Novels-ebook/dp/B00FVW5GBK?tag=thenewyorktim-20",
        "contributor": "by Faye Kellerman",
        "title": "MURDER 101",
        "sunday_review_link": "",
        "contributor_note": "",
        "isbns": [
          {
            "isbn10": "0062270184",
            "isbn13": "9780062270184"
          }
        ],
        "publisher": "Morrow"
      },
      {
        "price": 0,
        "primary_isbn10": "1101609508",
        "asterisk": 0,
        "dagger": 0,
        "author": "Patricia Briggs",
        "primary_isbn13": "9781101609507",
        "description": "",
        "book_review_link": "",
        "book_image_height": 193,
        "book_image": "https://s1.nyt.com/du/books/images/9780425265000.jpg",
        "rank": 17,
        "article_chapter_link": "",
        "rank_last_week": 0,
        "book_image_width": 128,
        "first_chapter_link": "",
        "age_group": "",
        "weeks_on_list": 0,
        "amazon_product_url": "http://www.amazon.com/Shifting-Shadows-Stories-World-Thompson/dp/0425265005?tag=thenewyorktim-20",
        "contributor": "by Patricia Briggs",
        "title": "SHIFTING SHADOWS",
        "sunday_review_link": "",
        "contributor_note": "",
        "isbns": [
          {
            "isbn10": "0425265005",
            "isbn13": "9780425265000"
          },
          {
            "isbn10": "1101609508",
            "isbn13": "9781101609507"
          }
        ],
        "publisher": "Ace"
      },
      {
        "price": 0,
        "primary_isbn10": "0440335183",
        "asterisk": 0,
        "dagger": 0,
        "author": "Diana Gabaldon",
        "primary_isbn13": "9780440335184",
        "description": "Volume 2 of the Outlander series, about an 18th-century Scottish warrior and a time-traveling World War II-era nurse; first published in 1992.",
        "book_review_link": "",
        "book_image_height": 475,
        "book_image": "https://s1.nyt.com/du/books/images/9780440335184.jpg",
        "rank": 18,
        "article_chapter_link": "",
        "rank_last_week": 0,
        "book_image_width": 314,
        "first_chapter_link": "",
        "age_group": "",
        "weeks_on_list": 0,
        "amazon_product_url": "http://www.amazon.com/Dragonfly-Amber-Outlander-Book-2-ebook/dp/B000FC2L28?tag=thenewyorktim-20",
        "contributor": "by Diana Gabaldon",
        "title": "DRAGONFLY IN AMBER",
        "sunday_review_link": "",
        "contributor_note": "",
        "isbns": [
          {
            "isbn10": "0440215625",
            "isbn13": "9780440215622"
          },
          {
            "isbn10": "0440335183",
            "isbn13": "9780440335184"
          },
          {
            "isbn10": "0385335970",
            "isbn13": "9780385335973"
          }
        ],
        "publisher": "Dell"
      },
      {
        "price": 0,
        "primary_isbn10": "",
        "asterisk": 0,
        "dagger": 0,
        "author": "Donna Tartt",
        "primary_isbn13": "9780316248679",
        "description": "After his mother is killed in a museum explosion, a young man grapples with the world alone while hiding a prized Dutch painting.",
        "book_review_link": "//www.nytimes.com/2013/10/08/books/the-goldfinch-a-dickensian-novel-by-donna-tartt.html",
        "book_image_height": 500,
        "book_image": "https://s1.nyt.com/du/books/images/9780316248679.jpg",
        "rank": 19,
        "article_chapter_link": "",
        "rank_last_week": 0,
        "book_image_width": 326,
        "first_chapter_link": "",
        "age_group": "",
        "weeks_on_list": 0,
        "amazon_product_url": "http://www.amazon.com/The-Goldfinch-Novel-Pulitzer-Fiction-ebook/dp/B00BAXFECK?tag=thenewyorktim-20",
        "contributor": "by Donna Tartt",
        "title": "THE GOLDFINCH",
        "sunday_review_link": "//www.nytimes.com/2013/10/13/books/review/donna-tartts-goldfinch.html",
        "contributor_note": "",
        "isbns": [
          {
            "isbn10": "0316055433",
            "isbn13": "9780316055437"
          },
          {
            "isbn10": "0316239879",
            "isbn13": "9780316239875"
          },
          {
            "isbn10": "0316055441",
            "isbn13": "9780316055444"
          },
          {
            "isbn10": "0349139636",
            "isbn13": "9780349139630"
          }
        ],
        "publisher": "Little, Brown"
      },
      {
        "price": 0,
        "primary_isbn10": "",
        "asterisk": 0,
        "dagger": 0,
        "author": "Christina Baker Kline",
        "primary_isbn13": "9780062101204",
        "description": "A historical novel about orphans swept off the streets of New York and sent to the Midwest in the 1920s.\u00a0",
        "book_review_link": "",
        "book_image_height": 500,
        "book_image": "https://s1.nyt.com/du/books/images/9780062101204.jpg",
        "rank": 20,
        "article_chapter_link": "",
        "rank_last_week": 0,
        "book_image_width": 332,
        "first_chapter_link": "",
        "age_group": "",
        "weeks_on_list": 0,
        "amazon_product_url": "http://www.amazon.com/Orphan-Train-Christina-Baker-Kline-ebook/dp/B0089LOG02?tag=thenewyorktim-20",
        "contributor": "by Christina Baker Kline",
        "title": "ORPHAN TRAIN",
        "sunday_review_link": "",
        "contributor_note": "",
        "isbns": [
          {
            "isbn10": "0061950726",
            "isbn13": "9780061950728"
          },
          {
            "isbn10": "1594137374",
            "isbn13": "9781594137372"
          },
          {
            "isbn10": "0606356649",
            "isbn13": "9780606356640"
          },
          {
            "isbn10": "006195070X",
            "isbn13": "9780061950704"
          }
        ],
        "publisher": "Morrow/HarperCollins"
      }
    ],
    "published_date_description": "",
    "display_name": "Combined Print & E-Book Fiction",
    "bestsellers_date": "2014-09-06",
    "previous_published_date": "2014-09-14",
    "normal_list_ends_at": 15,
    "corrections": [],
    "list_name_encoded": "combined-print-and-e-book-fiction",
    "next_published_date": "2014-09-28"
  },
  "status": "OK",
  "num_results": 20,
  "copyright": "Copyright (c) 2016 The New York Times Company.  All Rights Reserved."
}